deduplify/__init__.py
deduplify/_version.py
deduplify/cli.py
deduplify/compare_files.py
deduplify/del_empty_dirs.py
deduplify/hash_files.py
deduplify-20.9.0.dist-info/LICENSE
deduplify-20.9.0.dist-info/METADATA
deduplify-20.9.0.dist-info/WHEEL
deduplify-20.9.0.dist-info/entry_points.txt
deduplify-20.9.0.dist-info/top_level.txt
deduplify-20.9.0.dist-info/RECORD
