Metadata-Version: 2.1
Name: deduplify
Version: 20.9.0
Summary: A Python package to search for and remove duplicated files in messy datasets
Home-page: https://github.com/Living-with-Machines/deduplify
Author: Sarah Gibson
Author-email: sgibson@turing.ac.uk
License: MIT
Platform: UNKNOWN
Classifier: License :: OSI Approved :: MIT License
Classifier: Programming Language :: Python
Classifier: Programming Language :: Python :: 3
Classifier: Programming Language :: Python :: 3.7
Requires-Python: >=3.7.0
Requires-Dist: incremental
Requires-Dist: tqdm
Provides-Extra: dev
Requires-Dist: pytest ; extra == 'dev'
Requires-Dist: coverage ; extra == 'dev'
Requires-Dist: incremental ; extra == 'dev'
Provides-Extra: docs
Provides-Extra: full
Provides-Extra: tests
Requires-Dist: pytest ; extra == 'tests'
Requires-Dist: coverage ; extra == 'tests'
